{
    "mode": "Perform",
    "ml_task": "binary_classification",
    "results_path": "AutoML_1",
    "total_time_limit": 1200,
    "model_time_limit": null,
    "algorithms": [
        "Random Forest",
        "Extra Trees",
        "LightGBM",
        "CatBoost",
        "Xgboost"
    ],
    "train_ensemble": true,
    "stack_models": false,
    "eval_metric": "f1",
    "validation_strategy": {
        "validation_type": "kfold",
        "k_folds": 5,
        "shuffle": true,
        "stratify": true,
        "random_seed": 1234,
        "X_path": "AutoML_1/X.data",
        "y_path": "AutoML_1/y.data",
        "results_path": "AutoML_1"
    },
    "verbose": 1,
    "explain_level": 1,
    "golden_features": true,
    "features_selection": false,
    "start_random_models": 5,
    "hill_climbing_steps": 2,
    "top_models_to_improve": 2,
    "boost_on_errors": false,
    "kmeans_features": false,
    "mix_encoding": false,
    "max_single_prediction_time": 0.5,
    "n_jobs": -1,
    "random_state": 1234,
    "saved": [
        "1_Default_LightGBM",
        "2_Default_Xgboost",
        "3_Default_CatBoost",
        "4_Default_RandomForest",
        "5_Default_ExtraTrees",
        "10_LightGBM",
        "6_Xgboost",
        "14_CatBoost",
        "18_RandomForest",
        "22_ExtraTrees",
        "11_LightGBM",
        "7_Xgboost",
        "15_CatBoost",
        "19_RandomForest",
        "23_ExtraTrees",
        "12_LightGBM",
        "8_Xgboost",
        "16_CatBoost",
        "20_RandomForest",
        "24_ExtraTrees",
        "13_LightGBM",
        "9_Xgboost",
        "17_CatBoost",
        "21_RandomForest",
        "25_ExtraTrees",
        "14_CatBoost_GoldenFeatures",
        "16_CatBoost_GoldenFeatures",
        "3_Default_CatBoost_GoldenFeatures",
        "26_CatBoost",
        "27_CatBoost",
        "28_CatBoost",
        "29_CatBoost",
        "30_Xgboost",
        "31_Xgboost",
        "32_ExtraTrees",
        "33_RandomForest",
        "34_RandomForest",
        "35_LightGBM",
        "36_Xgboost",
        "37_Xgboost",
        "38_LightGBM",
        "39_ExtraTrees",
        "40_Xgboost",
        "Ensemble"
    ],
    "fit_level": "finished",
    "best_model": "Ensemble",
    "load_on_predict": [
        "14_CatBoost",
        "16_CatBoost",
        "17_CatBoost",
        "26_CatBoost",
        "28_CatBoost",
        "29_CatBoost",
        "36_Xgboost",
        "38_LightGBM",
        "3_Default_CatBoost",
        "6_Xgboost",
        "7_Xgboost",
        "Ensemble"
    ]
}